{
  "entries": [
    {
      "date": "2026-04-20",
      "timestamp": "2026-04-20T04:23:11",
      "title": "What Is Stock Trading? A Simple 2026 Guide for New Investors",
      "url": "https://fixailab.blogspot.com/2026/04/stock-trading-simple-investors-2026.html",
      "category": "Finance & Investing",
      "keyword": ""
    },
    {
      "date": "2026-04-20",
      "timestamp": "2026-04-20T14:48:09",
      "title": "Savings Strategies: Why You Should Maximize Your Bank Deposits in 2026",
      "url": "https://fixailab.blogspot.com/2026/04/savings-strategies-you-should-maximize.html",
      "category": "Finance & Investing",
      "keyword": "예금"
    },
    {
      "date": "2026-04-21",
      "timestamp": "2026-04-21T04:13:54",
      "title": "How ETFs Work: A Simple Guide for Your 2026 Investment Strategy",
      "url": "https://fixailab.blogspot.com/2026/04/etfs-work-simple-your-investment-2026.html",
      "category": "Finance & Investing",
      "keyword": ""
    },
    {
      "date": "2026-04-21",
      "timestamp": "2026-04-21T14:47:42",
      "title": "대출 3가지 핵심 전략: 2026년 금리 환경에서 손실 줄이는 법",
      "url": "https://fixailab.blogspot.com/2026/04/key-loan-strategies-reduce-losses-2026.html",
      "category": "Finance & Investing",
      "keyword": "대출"
    },
    {
      "date": "2026-04-22",
      "timestamp": "2026-04-22T04:10:00",
      "title": "How Stock Investing Works: A Simple 2026 Guide for Beginners",
      "url": "https://fixailab.blogspot.com/2026/04/stock-investing-works-simple-beginners.html",
      "category": "Finance & Investing",
      "keyword": ""
    },
    {
      "date": "2026-04-24",
      "timestamp": "2026-04-24T13:15:43",
      "title": "How to Buy Your First Stock: A Simple 4-Step Guide for 2026",
      "url": "https://fixailab.blogspot.com/2026/04/buy-your-first-stock-simple-2026.html",
      "category": "Finance & Investing",
      "keyword": ""
    },
    {
      "date": "2026-04-24",
      "timestamp": "2026-04-24T13:39:22",
      "title": "How to Save $5,000 in 2026: A Practical Financial Strategy",
      "url": "https://fixailab.blogspot.com/2026/04/save-practical-financial-strategy-2026.html",
      "category": "Finance & Investing",
      "keyword": "절약"
    },
    {
      "date": "2026-04-27",
      "timestamp": "2026-04-27T15:12:28",
      "title": "Stable Diffusion vs Midjourney: Which Image Tool Fits You in 2026",
      "url": "https://fixailab.blogspot.com/2026/04/stable-diffusion-vs-midjourney-image.html",
      "category": "Finance & Investing",
      "keyword": ""
    },
    {
      "date": "2026-04-28",
      "timestamp": "2026-04-28T04:30:55",
      "title": "How AI Productivity Tools Can Save You 10 Hours Every Week",
      "url": "https://fixailab.blogspot.com/2026/04/ai-productivity-tools-can-save-2026.html",
      "category": "Technology & AI",
      "keyword": ""
    },
    {
      "date": "2026-04-29",
      "timestamp": "2026-04-29T04:25:36",
      "title": "Voice AI: 3 Practical Ways to Improve Productivity in 2026",
      "url": "https://fixailab.blogspot.com/2026/04/voice-ai-practical-improve-productivity.html",
      "category": "Technology & AI",
      "keyword": ""
    },
    {
      "date": "2026-04-30",
      "timestamp": "2026-04-30T04:28:12",
      "title": "How a Structured AI Workflow Saves You 10 Hours Per Week in 2026",
      "url": "https://fixailab.blogspot.com/2026/04/structured-ai-workflow-saves-you-2026.html",
      "category": "Technology & AI",
      "keyword": ""
    },
    {
      "date": "2026-04-30",
      "timestamp": "2026-04-30T15:17:21",
      "title": "AI for Beginners: 5 Practical Steps to Start in 2026",
      "url": "https://fixailab.blogspot.com/2026/05/ai-beginners-practical-steps-start-2026.html",
      "category": "Technology & AI",
      "keyword": "AI for beginners"
    },
    {
      "date": "2026-05-01",
      "timestamp": "2026-05-01T04:44:02",
      "title": "How Midjourney Can Save You 10 Hours of Design Work Every Week",
      "url": "https://fixailab.blogspot.com/2026/05/midjourney-can-save-you-hours-2026.html",
      "category": "Technology & AI",
      "keyword": "Midjourney"
    },
    {
      "date": "2026-05-01",
      "timestamp": "2026-05-01T14:20:16",
      "title": "How to Master AI: 5 Practical Steps to Start in 2026",
      "url": "https://fixailab.blogspot.com/2026/05/master-ai-practical-steps-start-2026.html",
      "category": "Technology & AI",
      "keyword": "AI tutorial"
    }
  ]
}